pyqec-0.9.0.dist-info/METADATA
pyqec-0.9.0.dist-info/WHEEL
pyqec/laboratory.py
pyqec/__init__.py
pyqec/classical.py
pyqec/quantum/__init__.py
pyqec/quantum/pauli.py
pyqec/sparse.py
pyqec/pyqec.abi3.so
pyqec-0.9.0.dist-info/RECORD
